data_sources_tracking/__init__.py
data_sources_tracking/admin.py
data_sources_tracking/apps.py
data_sources_tracking/choices.py
data_sources_tracking/filters.py
data_sources_tracking/models.py
data_sources_tracking/serializers.py
data_sources_tracking/urls.py
data_sources_tracking/views.py
data_sources_tracking/viewsets.py
data_sources_tracking/migrations/0001_initial.py
data_sources_tracking/migrations/0002_auto_20180314_0951.py
data_sources_tracking/migrations/0003_auto_20180330_0659.py
data_sources_tracking/migrations/0004_auto_20180418_1127.py
data_sources_tracking/migrations/0005_add_support_for_excel_types.py
data_sources_tracking/migrations/0006_add_file_field.py
data_sources_tracking/migrations/__init__.py
django_data_sources_tracking-0.9.1.dist-info/AUTHORS.rst
django_data_sources_tracking-0.9.1.dist-info/LICENSE
django_data_sources_tracking-0.9.1.dist-info/METADATA
django_data_sources_tracking-0.9.1.dist-info/WHEEL
django_data_sources_tracking-0.9.1.dist-info/top_level.txt
django_data_sources_tracking-0.9.1.dist-info/RECORD
