Metadata-Version: 2.1
Name: django-data-sources-tracking
Version: 0.9.1
Summary: Django app for dealing with files/data sources and tracking them.
Home-page: https://github.com/genomics-geek/django-data-sources-tracking
Author: Michael A. Gonzalez
Author-email: GonzalezMA@email.chop.edu
License: MIT
Keywords: django-data-sources-tracking
Platform: UNKNOWN
Classifier: Development Status :: 4 - Beta
Classifier: Framework :: Django :: 2.0
Classifier: Framework :: Django :: 2.1
Classifier: Framework :: Django :: 2.2
Classifier: Intended Audience :: Developers
Classifier: License :: OSI Approved :: BSD License
Classifier: Natural Language :: English
Classifier: Programming Language :: Python :: 3
Classifier: Programming Language :: Python :: 3.5
Classifier: Programming Language :: Python :: 3.6
Requires-Dist: djangorestframework (==3.10.3)
Requires-Dist: django-filter (==2.2.0)
Requires-Dist: django-genomix (==0.6.10)
Requires-Dist: django-model-utils (==3.2.0)
Requires-Dist: django-user-activities (==0.5.11)
